AUTHORS.md
LICENSE.md
MANIFEST.in
README.md
README.rst
requirements.txt
setup.py
odl/__init__.py
odl/connector.py
odl/exceptions.py
odl/flow.py
odl/instance.py
odl/node.py
odl/table.py
odl/topology.py
of/__init__.py
of/flow.py
python_odl.egg-info/PKG-INFO
python_odl.egg-info/SOURCES.txt
python_odl.egg-info/dependency_links.txt
python_odl.egg-info/pbr.json
python_odl.egg-info/requires.txt
python_odl.egg-info/top_level.txt