Metadata-Version: 1.1
Name: python-odl
Version: 0.0.3
Summary: Python 2.x library for OpenDayLight interations via REST API.
Home-page: http://github.com/SPRACE/python-odl/
Author: Beraldo Leal
Author-email: beraldo@ncc.unesp.br
License: LICENSE.md
Keywords: odl,opendayligh,sdn,openflow,python,library,rest,api
Platform: Posix; MacOS X;
Classifier: Development Status :: 2 - Pre-Alpha
Classifier: Intended Audience :: Developers
Classifier: License :: OSI Approved :: GNU General Public License v3 (GPLv3)
Classifier: Operating System :: POSIX
Classifier: Topic :: Software Development :: Libraries :: Python Modules
Classifier: Topic :: Internet
Classifier: Topic :: System :: Networking
Classifier: Programming Language :: Python :: 2.7
